sigtools/__init__.py
sigtools/_autoforwards.py
sigtools/_signatures.py
sigtools/_specifiers.py
sigtools/_util.py
sigtools/modifiers.py
sigtools/signatures.py
sigtools/specifiers.py
sigtools/sphinxext.py
sigtools/support.py
sigtools/wrappers.py
sigtools/tests/__init__.py
sigtools/tests/sphinxextfixt.py
sigtools/tests/test_autoforwards.py
sigtools/tests/test_autoforwards_pep563.py
sigtools/tests/test_combination.py
sigtools/tests/test_decorator.py
sigtools/tests/test_embed.py
sigtools/tests/test_forwards.py
sigtools/tests/test_mask.py
sigtools/tests/test_merge.py
sigtools/tests/test_modifiers.py
sigtools/tests/test_signatures.py
sigtools/tests/test_specifiers.py
sigtools/tests/test_sphinxext.py
sigtools/tests/test_support.py
sigtools/tests/test_testutil.py
sigtools/tests/test_wrapper_decorator.py
sigtools/tests/util.py
sigtools-4.0.0.dist-info/LICENSE
sigtools-4.0.0.dist-info/METADATA
sigtools-4.0.0.dist-info/WHEEL
sigtools-4.0.0.dist-info/top_level.txt
sigtools-4.0.0.dist-info/RECORD
