Metadata-Version: 2.1
Name: sigtools
Version: 4.0.0
Summary: Utilities for working with inspect.Signature objects.
Home-page: https://sigtools.readthedocs.io/
Author: Yann Kaiser
Author-email: kaiser.yann@gmail.com
License: MIT
Keywords: introspection signature
Classifier: Development Status :: 5 - Production/Stable
Classifier: Intended Audience :: Developers
Classifier: License :: OSI Approved :: MIT License
Classifier: Operating System :: OS Independent
Classifier: Programming Language :: Python :: 3
Classifier: Programming Language :: Python :: 3.4
Classifier: Programming Language :: Python :: 3.5
Classifier: Programming Language :: Python :: 3.6
Classifier: Programming Language :: Python :: 3.7
Classifier: Programming Language :: Python :: 3.8
Classifier: Programming Language :: Python :: 3.9
Classifier: Topic :: Software Development :: Libraries :: Python Modules
Requires-Python: >=3.6
License-File: LICENSE
Requires-Dist: attrs
Provides-Extra: test
Requires-Dist: repeated-test (>=2.2.1) ; extra == 'test'
Requires-Dist: sphinx ; extra == 'test'
Requires-Dist: mock ; extra == 'test'
Requires-Dist: coverage ; extra == 'test'
Provides-Extra: tests
Requires-Dist: repeated-test (>=2.2.1) ; extra == 'tests'
Requires-Dist: sphinx ; extra == 'tests'
Requires-Dist: mock ; extra == 'tests'
Requires-Dist: coverage ; extra == 'tests'
